apsjournals/__init__.py
apsjournals/api.py
apsjournals/journals.py
apsjournals/pdf.py
apsjournals/util.py
apsjournals/web/__init__.py
apsjournals/web/auth.py
apsjournals/web/constants.py
apsjournals/web/scrapers.py
tests/__init__.py
tests/test_api.py
tests/test_constants.py
tests/test_pdf.py
tests/test_scrapers.py
apsjournals-0.2.0.dist-info/LICENSE
apsjournals-0.2.0.dist-info/METADATA
apsjournals-0.2.0.dist-info/WHEEL
apsjournals-0.2.0.dist-info/top_level.txt
apsjournals-0.2.0.dist-info/RECORD
