Metadata-Version: 2.1
Name: apsjournals
Version: 0.2.0
Summary: A pythonic interface for APS publications
Home-page: http://github.com/JWKennington/apsjournals
Author: James W. Kennington
Author-email: jameswkennington@gmail.com
License: MIT
Platform: UNKNOWN
